giclient/__init__.py
giclient/authentication.py
giclient/client.py
giclient/event_hooks.py
giclient/manager.py
giclient/transport.py
giclient/services/__init__.py
giclient/services/account.py
giclient/services/accounting.py
giclient/services/businesses.py
giclient/services/clients.py
giclient/services/documents.py
giclient/services/expenses.py
giclient/services/items.py
giclient/services/partners.py
giclient/services/payments.py
giclient/services/suppliers.py
giclient/services/shared/get_update_delete.py
giclient/services/shared/search.py
python_greeninvoice_client-0.1.4.dist-info/licenses/LICENSE
python_greeninvoice_client-0.1.4.dist-info/METADATA
python_greeninvoice_client-0.1.4.dist-info/WHEEL
python_greeninvoice_client-0.1.4.dist-info/top_level.txt
python_greeninvoice_client-0.1.4.dist-info/RECORD
