Metadata-Version: 2.4
Name: python-greeninvoice-client
Version: 0.1.4
Author: UniProBI
Maintainer-email: uriah372@gmail.com
License: MIT License
Project-URL: Repository, https://github.com/UniProBI/python-greeninvoice-client.git
Project-URL: Issues, https://github.com/UniProBI/python-greeninvoice-client/issues
Keywords: greeninvoice,green,invoice,python,api,client
Requires-Python: >=3.12
License-File: LICENSE
Requires-Dist: httpx
Requires-Dist: aiolimiter
Requires-Dist: yarl
Dynamic: license-file
